hnswlib.cpython-310-x86_64-linux-gnu.so
prebuilt_hnsw.libs/libstdc++-0d31ccbe.so.6.0.32
prebuilt_hnsw.libs/libgcc_s-a0b57c20.so.1
prebuilt_hnsw-0.8.1.dist-info/top_level.txt
prebuilt_hnsw-0.8.1.dist-info/RECORD
prebuilt_hnsw-0.8.1.dist-info/LICENSE
prebuilt_hnsw-0.8.1.dist-info/METADATA
prebuilt_hnsw-0.8.1.dist-info/WHEEL
