Metadata-Version: 2.1
Name: prebuilt-hnsw
Version: 0.8.1
Summary: Prebuilt wheels for hnswlib
Home-page: https://github.com/nmslib/hnswlib
Author: Romlin Group AB (prebuilt wheels); Original authors: Yury Malkov and others
Classifier: Development Status :: 4 - Beta
Classifier: Intended Audience :: Science/Research
Classifier: License :: OSI Approved :: Apache Software License
Classifier: Programming Language :: Python :: 3 :: Only
Classifier: Topic :: Scientific/Engineering
Requires-Python: >=3.10
License-File: LICENSE
Requires-Dist: numpy
